types_www_authenticate-0.9.0.20260130.dist-info/licenses/LICENSE
www_authenticate-stubs/METADATA.toml
www_authenticate-stubs/__init__.pyi
www_authenticate-stubs/py.typed
types_www_authenticate-0.9.0.20260130.dist-info/METADATA
types_www_authenticate-0.9.0.20260130.dist-info/WHEEL
types_www_authenticate-0.9.0.20260130.dist-info/top_level.txt
types_www_authenticate-0.9.0.20260130.dist-info/RECORD
